README.rst
setup.py
xltable/__init__.py
xltable/chart.py
xltable/expression.py
xltable/style.py
xltable/table.py
xltable/workbook.py
xltable/worksheet.py
xltable.egg-info/PKG-INFO
xltable.egg-info/SOURCES.txt
xltable.egg-info/dependency_links.txt
xltable.egg-info/requires.txt
xltable.egg-info/top_level.txt