Metadata-Version: 1.1
Name: xltable
Version: 0.2.3
Summary: A Python package to ease writing tables of data to Excel
Home-page: https://github.com/fkarb/xltable
Author: Renshaw Bay
Author-email: tony@pyxll.com
License: UNKNOWN
Platform: UNKNOWN
Classifier: License :: OSI Approved :: MIT License
